Metadata-Version: 2.1
Name: th2-grpc-act-template
Version: 4.4.0
Summary: th2_grpc_act_template
Home-page: https://github.com/th2-net/th2-grpc-act-template
Author: TH2-devs
Author-email: th2-devs@exactprosystems.com
License: Apache License 2.0
Requires-Python: >=3.7
License-File: LICENSE
